anexo2/__init__.py
anexo2/docs.py
anexo2/templates/anexo2.css
anexo2/templates/anexo2.html
anexo2-1.0.21.dist-info/METADATA
anexo2-1.0.21.dist-info/WHEEL
anexo2-1.0.21.dist-info/top_level.txt
anexo2-1.0.21.dist-info/RECORD
