Metadata-Version: 2.1
Name: anexo2
Version: 1.0.21
Summary: Generacion de HTML para impresion de Anexo II
Home-page: https://github.com/cluster311/Anexo2
Author: Andres Vazquez
Author-email: andres@data99.com.ar
License: MIT
Platform: UNKNOWN
Classifier: Programming Language :: Python :: 3
Classifier: Programming Language :: Python :: 3.6
Classifier: License :: OSI Approved :: MIT License
Classifier: Operating System :: OS Independent
Classifier: Intended Audience :: Developers
Requires-Python: >=3.6
Requires-Dist: cerberus (>=1.3)
Requires-Dist: jinja2
